ShiyongTensorflowGoujianJiqiXuexiXiangmuZhongwenbanChuyiFix1/README.md
ShiyongTensorflowGoujianJiqiXuexiXiangmuZhongwenbanChuyiFix1/__init__.py
ShiyongTensorflowGoujianJiqiXuexiXiangmuZhongwenbanChuyiFix1/__main__.py
ShiyongTensorflowGoujianJiqiXuexiXiangmuZhongwenbanChuyiFix1/file.epub
ShiyongTensorflowGoujianJiqiXuexiXiangmuZhongwenbanChuyiFix1/index.html
ShiyongTensorflowGoujianJiqiXuexiXiangmuZhongwenbanChuyiFix1/css/__init__.py
ShiyongTensorflowGoujianJiqiXuexiXiangmuZhongwenbanChuyiFix1/css/annotations.css
ShiyongTensorflowGoujianJiqiXuexiXiangmuZhongwenbanChuyiFix1/css/main.css
ShiyongTensorflowGoujianJiqiXuexiXiangmuZhongwenbanChuyiFix1/css/normalize.css
ShiyongTensorflowGoujianJiqiXuexiXiangmuZhongwenbanChuyiFix1/css/popup.css
ShiyongTensorflowGoujianJiqiXuexiXiangmuZhongwenbanChuyiFix1/font/__init__.py
ShiyongTensorflowGoujianJiqiXuexiXiangmuZhongwenbanChuyiFix1/font/fontello.eot
ShiyongTensorflowGoujianJiqiXuexiXiangmuZhongwenbanChuyiFix1/font/fontello.svg
ShiyongTensorflowGoujianJiqiXuexiXiangmuZhongwenbanChuyiFix1/font/fontello.ttf
ShiyongTensorflowGoujianJiqiXuexiXiangmuZhongwenbanChuyiFix1/font/fontello.woff
ShiyongTensorflowGoujianJiqiXuexiXiangmuZhongwenbanChuyiFix1/img/__init__.py
ShiyongTensorflowGoujianJiqiXuexiXiangmuZhongwenbanChuyiFix1/img/annotator-glyph-sprite.png
ShiyongTensorflowGoujianJiqiXuexiXiangmuZhongwenbanChuyiFix1/img/annotator-icon-sprite.png
ShiyongTensorflowGoujianJiqiXuexiXiangmuZhongwenbanChuyiFix1/img/apple-touch-icon.png
ShiyongTensorflowGoujianJiqiXuexiXiangmuZhongwenbanChuyiFix1/img/cancelfullscreen.png
ShiyongTensorflowGoujianJiqiXuexiXiangmuZhongwenbanChuyiFix1/img/close.png
ShiyongTensorflowGoujianJiqiXuexiXiangmuZhongwenbanChuyiFix1/img/fullscreen.png
ShiyongTensorflowGoujianJiqiXuexiXiangmuZhongwenbanChuyiFix1/img/loader.gif
ShiyongTensorflowGoujianJiqiXuexiXiangmuZhongwenbanChuyiFix1/img/menu-icon.png
ShiyongTensorflowGoujianJiqiXuexiXiangmuZhongwenbanChuyiFix1/img/save.png
shiyong_tensorflow_goujian_jiqi_xuexi_xiangmu_zhongwenban_chuyi_fix1-2025.3.24.0.dist-info/METADATA
shiyong_tensorflow_goujian_jiqi_xuexi_xiangmu_zhongwenban_chuyi_fix1-2025.3.24.0.dist-info/WHEEL
shiyong_tensorflow_goujian_jiqi_xuexi_xiangmu_zhongwenban_chuyi_fix1-2025.3.24.0.dist-info/entry_points.txt
shiyong_tensorflow_goujian_jiqi_xuexi_xiangmu_zhongwenban_chuyi_fix1-2025.3.24.0.dist-info/top_level.txt
shiyong_tensorflow_goujian_jiqi_xuexi_xiangmu_zhongwenban_chuyi_fix1-2025.3.24.0.dist-info/RECORD
